dist_alx_test/Binomialdistribution.py
dist_alx_test/Gaussiandistribution.py
dist_alx_test/Generaldistribution.py
dist_alx_test/__init__.py
dist_alx_test-0.1.dist-info/METADATA
dist_alx_test-0.1.dist-info/WHEEL
dist_alx_test-0.1.dist-info/top_level.txt
dist_alx_test-0.1.dist-info/RECORD
