Metadata-Version: 2.1
Name: dist-alx-test
Version: 0.1
Summary: Gaussian and Binomial distributions
Home-page: UNKNOWN
Author-email: jayantreddybodkurwar@gmail.com
License: UNKNOWN
Platform: UNKNOWN
